ollama_downloads/__init__.py
ollama_downloads/ollama_downloads_process.py
ollama_downloads-0.1.2.dist-info/LICENSE
ollama_downloads-0.1.2.dist-info/METADATA
ollama_downloads-0.1.2.dist-info/WHEEL
ollama_downloads-0.1.2.dist-info/RECORD
