Metadata-Version: 2.1
Name: ollama-downloads
Version: 0.1.2
Summary: 
Author: Kenneth Wong
Author-email: kennethwork101@gmail.com
Requires-Python: >=3.10,<4.0
Classifier: Programming Language :: Python :: 3
Classifier: Programming Language :: Python :: 3.10
Classifier: Programming Language :: Python :: 3.11
Classifier: Programming Language :: Python :: 3.12
Requires-Dist: kwwutils (>=0.1.1,<0.2.0)
Requires-Dist: selenium (>=4.18.1,<5.0.0)
Requires-Dist: tqdm (>=4.66.2,<5.0.0)
Requires-Dist: transformers (>=4.39.1,<5.0.0)
